etlassist/__init__.py
etlassist/xml_generator.py
etlassist-0.0.3.dist-info/LICENSE
etlassist-0.0.3.dist-info/METADATA
etlassist-0.0.3.dist-info/WHEEL
etlassist-0.0.3.dist-info/top_level.txt
etlassist-0.0.3.dist-info/RECORD
