Metadata-Version: 2.1
Name: etlassist
Version: 0.0.3
Summary: etlassist is a python package supporting ETL operations
Author: Gokul Kumar Jayaram
Author-email: <gokulkumar.jayaram@gmail.com>
Keywords: python,etlassist,packaging,etl operations,databricks
Classifier: Development Status :: 1 - Planning
Classifier: Intended Audience :: Developers
Classifier: Programming Language :: Python :: 3
Classifier: Operating System :: Unix
Classifier: Operating System :: MacOS :: MacOS X
Classifier: Operating System :: Microsoft :: Windows
License-File: LICENSE
Requires-Dist: lxml
